odoo/addons/oca_all/README.rst
odoo/addons/oca_all/__init__.py
odoo/addons/oca_all/__manifest__.py
odoo/addons/oca_all/i18n/oca_all.pot
odoo/addons/oca_all/readme/DESCRIPTION.rst
odoo/addons/oca_all/static/description/icon.png
odoo/addons/oca_all/static/description/index.html
odoo14_addon_oca_all-14.0.0.0.2.dev10.dist-info/METADATA
odoo14_addon_oca_all-14.0.0.0.2.dev10.dist-info/WHEEL
odoo14_addon_oca_all-14.0.0.0.2.dev10.dist-info/top_level.txt
odoo14_addon_oca_all-14.0.0.0.2.dev10.dist-info/RECORD
