Metadata-Version: 2.1
Name: odoo14-addon-oca_all
Version: 14.0.0.0.2.dev10
Summary: All oca modules dependencies
Home-page: https://github.com/OCA/oca-custom
Author: Pierre Verkest <pierre@verkest.fr>, Odoo Community Association (OCA)
Author-email: support@odoo-community.org
License: AGPL-3
Classifier: Programming Language :: Python
Classifier: Framework :: Odoo
Classifier: Framework :: Odoo :: 14.0
Classifier: License :: OSI Approved :: GNU Affero General Public License v3
Classifier: Development Status :: 3 - Alpha
Requires-Python: >=3.6
Requires-Dist: odoo14-addon-account-banking-pain-base
Requires-Dist: odoo14-addon-account-banking-sepa-credit-transfer
Requires-Dist: odoo14-addon-account-credit-control
Requires-Dist: odoo14-addon-account-financial-report
Requires-Dist: odoo14-addon-account-lock-to-date
Requires-Dist: odoo14-addon-account-menu
Requires-Dist: odoo14-addon-account-payment-mode
Requires-Dist: odoo14-addon-account-payment-order
Requires-Dist: odoo14-addon-account-payment-partner
Requires-Dist: odoo14-addon-account-payment-sale
Requires-Dist: odoo14-addon-account-payment-unece
Requires-Dist: odoo14-addon-account-reconciliation-widget
Requires-Dist: odoo14-addon-account-statement-import
Requires-Dist: odoo14-addon-account-statement-import-base
Requires-Dist: odoo14-addon-account-statement-import-online-wise
Requires-Dist: odoo14-addon-account-statement-import-paypal
Requires-Dist: odoo14-addon-account-statement-import-txt-xlsx
Requires-Dist: odoo14-addon-account-tax-unece
Requires-Dist: odoo14-addon-apps-download
Requires-Dist: odoo14-addon-apps-product-creator
Requires-Dist: odoo14-addon-base-deterministic-session-gc
Requires-Dist: odoo14-addon-base-technical-features
Requires-Dist: odoo14-addon-base-ubl
Requires-Dist: odoo14-addon-base-ubl-payment
Requires-Dist: odoo14-addon-base-unece
Requires-Dist: odoo14-addon-bi-sql-editor
Requires-Dist: odoo14-addon-crowdfunding
Requires-Dist: odoo14-addon-currency-rate-update
Requires-Dist: odoo14-addon-date-range
Requires-Dist: odoo14-addon-disable-odoo-online
Requires-Dist: odoo14-addon-document-page
Requires-Dist: odoo14-addon-event-badge-design
Requires-Dist: odoo14-addon-github-connector
Requires-Dist: odoo14-addon-github-connector-oca
Requires-Dist: odoo14-addon-github-connector-odoo
Requires-Dist: odoo14-addon-knowledge
Requires-Dist: odoo14-addon-l10n-ch-base-bank
Requires-Dist: odoo14-addon-l10n-ch-pain-base
Requires-Dist: odoo14-addon-l10n-ch-pain-credit-transfer
Requires-Dist: odoo14-addon-mass-editing
Requires-Dist: odoo14-addon-mass-operation-abstract
Requires-Dist: odoo14-addon-membership-delegated-partner-line
Requires-Dist: odoo14-addon-membership-extension
Requires-Dist: odoo14-addon-mis-builder
Requires-Dist: odoo14-addon-mis-builder-budget
Requires-Dist: odoo14-addon-mis-builder-cash-flow
Requires-Dist: odoo14-addon-mis-builder-demo
Requires-Dist: odoo14-addon-multi-step-wizard
Requires-Dist: odoo14-addon-oca-custom
Requires-Dist: odoo14-addon-oca-psc-team
Requires-Dist: odoo14-addon-partner-contact-access-link
Requires-Dist: odoo14-addon-partner-statement
Requires-Dist: odoo14-addon-project-members
Requires-Dist: odoo14-addon-project-task-add-very-high
Requires-Dist: odoo14-addon-report-xlsx
Requires-Dist: odoo14-addon-report-xlsx-helper
Requires-Dist: odoo14-addon-sentry
Requires-Dist: odoo14-addon-sql-request-abstract
Requires-Dist: odoo14-addon-survey-xlsx
Requires-Dist: odoo14-addon-uom-unece
Requires-Dist: odoo14-addon-web-advanced-search
Requires-Dist: odoo14-addon-web-refresher
Requires-Dist: odoo14-addon-web-responsive
Requires-Dist: odoo14-addon-web-search-with-and
Requires-Dist: odoo14-addon-web-widget-dropdown-dynamic
Requires-Dist: odoo14-addon-website-apps-store
Requires-Dist: odoo14-addon-website-oca-integrator
Requires-Dist: odoo14-addon-website-oca-psc-team
Requires-Dist: odoo<14.1dev,>=14.0a
